setup.py
punnoose_weather/__init__.py
punnoose_weather/punnoose_weather.py
punnoose_weather.egg-info/PKG-INFO
punnoose_weather.egg-info/SOURCES.txt
punnoose_weather.egg-info/dependency_links.txt
punnoose_weather.egg-info/top_level.txt