Metadata-Version: 2.1
Name: punnoose-weather
Version: 2.0
Summary: Punnoose Weather
Home-page: UNKNOWN
Author: Punnoose
Author-email: punnoose.p@gmail.com
License: UNKNOWN
Platform: UNKNOWN
